import_expression/__init__.py
import_expression/__main__.py
import_expression/_codec.py
import_expression/_parser.py
import_expression/_repl.py
import_expression/_rewrite.py
import_expression/_syntax.py
import_expression/constants.py
import_expression/utils.py
import_expression/version.py
import_expression-2.2.1.dist-info/LICENSE
import_expression-2.2.1.dist-info/LICENSE-header
import_expression-2.2.1.dist-info/METADATA
import_expression-2.2.1.dist-info/WHEEL
import_expression-2.2.1.dist-info/entry_points.txt
import_expression-2.2.1.dist-info/top_level.txt
import_expression-2.2.1.dist-info/RECORD
