Metadata-Version: 2.1
Name: import_expression
Version: 2.2.1
Summary: Parses a superset of Python allowing for inline module import expressions
Home-page: https://github.com/ioistired/import-expression
Author: io mintz
Author-email: io@mintz.cc
License: MIT
Classifier: License :: OSI Approved :: MIT License
License-File: LICENSE
License-File: LICENSE-header
Provides-Extra: test
Requires-Dist: pytest; extra == "test"
Requires-Dist: pytest-cov; extra == "test"
